README.md
setup.cfg
setup.py
el_validator/__init__.py
el_validator/__version__.py
el_validator/validator.py
el_validator.egg-info/PKG-INFO
el_validator.egg-info/SOURCES.txt
el_validator.egg-info/dependency_links.txt
el_validator.egg-info/requires.txt
el_validator.egg-info/top_level.txt